powergim/__init__.py
powergim/cost_analysis.py
powergim/dcmp_tools/README.md
powergim/dcmp_tools/__init__.py
powergim/dcmp_tools/bd.py
powergim/dcmp_tools/decomposition.py
powergim/dcmp_tools/evpi.py
powergim/dcmp_tools/results_plots.py
powergim/dcmp_tools/utils_spi.py
powergim/dcmp_tools/vss.py
powergim/file_io.py
powergim/grid_data.py
powergim/investment_model.py
powergim/plots.py
powergim/plots_map.py
powergim/plots_map2.py
powergim/results.py
powergim/sampling.py
powergim/testcases.py
powergim/utils.py
powergim-1.1.0.dist-info/LICENSE
powergim-1.1.0.dist-info/METADATA
powergim-1.1.0.dist-info/WHEEL
powergim-1.1.0.dist-info/RECORD
