Metadata-Version: 2.3
Name: powergim
Version: 1.1.0
Summary: Power Grid Investment Module (PowerGIM)
License: MIT
Author: Harald G Svendsen
Author-email: harald.svendsen@sintef.no
Requires-Python: >=3.10
Classifier: License :: OSI Approved :: MIT License
Classifier: Programming Language :: Python :: 3
Classifier: Programming Language :: Python :: 3.10
Classifier: Programming Language :: Python :: 3.11
Classifier: Programming Language :: Python :: 3.12
Classifier: Programming Language :: Python :: 3.13
Provides-Extra: plotting
Requires-Dist: Pyomo (>=6.4.2)
Requires-Dist: branca ; extra == "plotting"
Requires-Dist: cloudpickle (>=2.2.0)
Requires-Dist: folium ; extra == "plotting"
Requires-Dist: geopandas (>=0.12.1)
Requires-Dist: highspy (>=1.9.0)
Requires-Dist: ipywidgets (>=8)
Requires-Dist: jinja2 ; extra == "plotting"
Requires-Dist: jupyterlab (>=3.4.7)
Requires-Dist: matplotlib ; extra == "plotting"
Requires-Dist: mpi-sppy (>=0.11.1)
Requires-Dist: mpi4py (>=3.1.1)
Requires-Dist: networkx (>=3.0)
Requires-Dist: numpy (>=1.23.0)
Requires-Dist: openpyxl (>=3.0.10)
Requires-Dist: pandas (>=1.5.0)
Requires-Dist: plotly ; extra == "plotting"
Requires-Dist: pydantic (>=1.10.0)
Requires-Dist: ruamel-yaml (>=0.18.10,<0.19.0)
Requires-Dist: scikit-learn (>=1.1.2)
Requires-Dist: scipy (>=1.9.1)
Requires-Dist: seaborn ; extra == "plotting"
Project-URL: Repository, https://github.com/powergama/powergim
